{
  "case_name": "Al-Skeini m.fl. mot Förenade kungariket",
  "application_no": "55721/07",
  "hudoc_id": "001-105606",
  "respondent_state": "Förenade kungariket",
  "date": "2011-07-07",
  "danelius_pages": "51, 85",
  "formation": "grand_chamber",
  "ecli": "ECLI:CE:ECHR:2011:0707JUD005572107",
  "importance": "1",
  "doctypebranch": "GRANDCHAMBER",
  "separate_opinion": "TRUE",
  "hudoc_docname": "CASE OF AL-SKEINI AND OTHERS v. THE UNITED KINGDOM",
  "hudoc_respondent": "GBR",
  "downloaded": true,
  "download_reason": "ok"
}