{
  "case_name": "Aubert m.fl. mot Frankrike",
  "application_no": "31501/03;31870/03;13045/04;13076/04;14838/04;17558/04;30488/04;45576/04;20389/05",
  "hudoc_id": "002-2895",
  "respondent_state": "Frankrike",
  "date": "2007-01-09",
  "danelius_pages": "365, 716",
  "formation": "chamber",
  "ecli": "",
  "importance": "4",
  "doctypebranch": "CLIN",
  "separate_opinion": "",
  "hudoc_docname": "Aubert and Others v. France",
  "hudoc_respondent": "FRA",
  "downloaded": true,
  "download_reason": "html",
  "download_render_note": null,
  "attempted_query": "docname:\"Aubert and others\" AND respondent:\"FRA\"",
  "match_score": 1.455813953488372,
  "match_name_score": 0.9058139534883721,
  "candidate_count": 12,
  "primary_candidate_itemid": "002-2895",
  "primary_candidate_docname": "Aubert and Others v. France"
}