{
  "case_name": "Caballero mot Förenade kungariket",
  "application_no": "32819/96",
  "hudoc_id": "001-58458",
  "respondent_state": "Förenade kungariket",
  "date": "2000-02-08",
  "danelius_pages": "162, 179",
  "formation": "grand_chamber",
  "ecli": "ECLI:CE:ECHR:2000:0208JUD003281996",
  "importance": "1",
  "doctypebranch": "GRANDCHAMBER",
  "separate_opinion": "TRUE",
  "hudoc_docname": "CASE OF CABALLERO v. THE UNITED KINGDOM",
  "hudoc_respondent": "GBR",
  "downloaded": true,
  "download_reason": "ok"
}