{
  "case_name": "Cumhuriyet Vali(t m.(l. mot Turkiet",
  "application_no": "28255/07",
  "hudoc_id": "001-126797",
  "respondent_state": "Turkiet",
  "date": "2013-10-08",
  "danelius_pages": "582",
  "formation": "chamber",
  "ecli": "ECLI:CE:ECHR:2013:1008JUD002825507",
  "importance": "3",
  "doctypebranch": "CHAMBER",
  "separate_opinion": "FALSE",
  "hudoc_docname": "CASE OF CUMHURİYET VAKFI AND OTHERS v. TURKEY",
  "hudoc_respondent": "TUR",
  "downloaded": true,
  "download_reason": "html",
  "download_render_note": null,
  "attempted_query": "respondent:\"TUR\" AND kpdate:\"2013-10-08\"",
  "match_score": 0.9453846153846155,
  "match_name_score": 0.3453846153846154,
  "candidate_count": 15,
  "primary_candidate_itemid": "001-127272",
  "primary_candidate_docname": "AFFAIRE CUMHURİYET VAKFI ET AUTRES c. TURQUIE"
}