{
  "case_name": "De Lesquen du Plessis-Casso (nr 2) mot Frankrike",
  "application_no": "34400/10",
  "hudoc_id": "001-140262",
  "respondent_state": "Frankrike",
  "date": "2014-01-30",
  "danelius_pages": "579",
  "formation": "chamber",
  "ecli": "ECLI:CE:ECHR:2014:0130JUD003440010",
  "importance": "4",
  "doctypebranch": "CHAMBER",
  "separate_opinion": "TRUE",
  "hudoc_docname": "AFFAIRE DE LESQUEN DU PLESSIS-CASSO c. FRANCE (N° 2)",
  "hudoc_respondent": "FRA",
  "downloaded": true,
  "download_reason": "html",
  "download_render_note": null,
  "attempted_query": "docname:\"De Lesquen du Plessis-Casso\" AND respondent:\"FRA\"",
  "match_score": 1.4740000000000002,
  "match_name_score": 0.8740000000000001,
  "candidate_count": 8,
  "primary_candidate_itemid": "001-140819",
  "primary_candidate_docname": "CASE OF DE LESQUEN DU PLESSIS-CASSO v. FRANCE (No. 2) "
}