{
  "case_name": "Felloni mot Italien (6.2.2020) 376, Fener Rum Patrikligi mot Turkiet",
  "application_no": "14340/05",
  "hudoc_id": "001-87396",
  "respondent_state": "Turkiet",
  "date": "2008-07-08",
  "danelius_pages": "721",
  "formation": "chamber",
  "ecli": "ECLI:CE:ECHR:2008:0708JUD001434005",
  "importance": "3",
  "doctypebranch": "CHAMBER",
  "separate_opinion": "TRUE",
  "hudoc_docname": "AFFAIRE FENER RUM PATRİKLİĞİ (PATRIARCAT OECUMENIQUE) c. TURQUIE",
  "hudoc_respondent": "TUR",
  "downloaded": true,
  "download_reason": "html",
  "download_render_note": null,
  "attempted_query": "docname:\"Fener Rum Patrikligi\" AND respondent:\"TUR\"",
  "match_score": 1.3722222222222222,
  "match_name_score": 0.7722222222222223,
  "candidate_count": 44,
  "primary_candidate_itemid": "001-87442",
  "primary_candidate_docname": "CASE OF FENER RUM PATRİKLİĞİ (ECUMENICAL PATRIARCHY) v. TURKEY"
}