{
  "case_name": "Granos Organicos Nacionales S.A. mot Tyskland",
  "application_no": "19508/07",
  "hudoc_id": "001-109807",
  "respondent_state": "Tyskland",
  "date": "2012-03-22",
  "danelius_pages": "227",
  "formation": "chamber",
  "ecli": "ECLI:CE:ECHR:2012:0322JUD001950807",
  "importance": "3",
  "doctypebranch": "CHAMBER",
  "separate_opinion": "FALSE",
  "hudoc_docname": "CASE OF GRANOS ORGANICOS NACIONALES S.A. v. GERMANY",
  "hudoc_respondent": "DEU",
  "downloaded": true,
  "download_reason": "ok"
}