{
  "case_name": "Ibrahim m.fl. mot Förenade kungariket",
  "application_no": "50541/08;50571/08;50573/08;40351/09",
  "hudoc_id": "001-148676",
  "respondent_state": "Förenade kungariket",
  "date": "2014-12-16",
  "danelius_pages": "413",
  "formation": "chamber",
  "ecli": "ECLI:CE:ECHR:2014:1216JUD005054108",
  "importance": "3",
  "doctypebranch": "CHAMBER",
  "separate_opinion": "TRUE",
  "hudoc_docname": "CASE OF IBRAHIM AND OTHERS v. THE UNITED KINGDOM",
  "hudoc_respondent": "GBR",
  "downloaded": true,
  "download_reason": "ok"
}