{
  "case_name": "Liepi,:,s mot Lettland",
  "application_no": "31855/03",
  "hudoc_id": "001-148174",
  "respondent_state": "Lettland",
  "date": "2014-11-25",
  "danelius_pages": "318",
  "formation": "chamber",
  "ecli": "ECLI:CE:ECHR:2014:1125JUD003185503",
  "importance": "4",
  "doctypebranch": "CHAMBER",
  "separate_opinion": "FALSE",
  "hudoc_docname": "CASE OF LIEPIŅŠ v. LATVIA",
  "hudoc_respondent": "LVA",
  "downloaded": true,
  "download_reason": "html",
  "download_render_note": null,
  "attempted_query": "respondent:\"LVA\" AND kpdate:\"2014-11-25\"",
  "match_score": 0.8032258064516129,
  "match_name_score": 0.2032258064516129,
  "candidate_count": 8,
  "primary_candidate_itemid": "001-148174",
  "primary_candidate_docname": "CASE OF LIEPIŅŠ v. LATVIA"
}