{
  "case_name": "lsakovic Vidovic mot Serbien",
  "application_no": "41694/07",
  "hudoc_id": "001-145215",
  "respondent_state": "Serbien",
  "date": "2014-07-01",
  "danelius_pages": "455",
  "formation": "chamber",
  "ecli": "ECLI:CE:ECHR:2014:0701JUD004169407",
  "importance": "4",
  "doctypebranch": "CHAMBER",
  "separate_opinion": "FALSE",
  "hudoc_docname": "CASE OF ISAKOVIĆ VIDOVIĆ v. SERBIA",
  "hudoc_respondent": "SRB",
  "downloaded": true,
  "download_reason": "html",
  "download_render_note": null,
  "attempted_query": "respondent:\"SRB\" AND kpdate:\"2014-07-01\"",
  "match_score": 1.1505102040816328,
  "match_name_score": 0.5505102040816328,
  "candidate_count": 6,
  "primary_candidate_itemid": "001-145215",
  "primary_candidate_docname": "CASE OF ISAKOVIĆ VIDOVIĆ v. SERBIA"
}