{
  "case_name": "Metzger mot Tyskland",
  "application_no": "37591/97",
  "hudoc_id": "001-64037",
  "respondent_state": "Tyskland",
  "date": "2001-05-31",
  "danelius_pages": "209",
  "formation": "chamber",
  "ecli": "ECLI:CE:ECHR:2001:0531JUD003759197",
  "importance": "4",
  "doctypebranch": "CHAMBER",
  "separate_opinion": "FALSE",
  "hudoc_docname": "AFFAIRE METZGER c. ALLEMAGNE",
  "hudoc_respondent": "DEU",
  "downloaded": true,
  "download_reason": "html",
  "download_render_note": null,
  "attempted_query": "docname:\"Metzger\" AND respondent:\"DEU\"",
  "match_score": 1.335294117647059,
  "match_name_score": 0.7352941176470589,
  "candidate_count": 10,
  "primary_candidate_itemid": "001-59479",
  "primary_candidate_docname": "CASE OF METZGER v. GERMANY"
}