{
  "case_name": "Sace Elektrik Ticaret ve Sanayi A.$. mot Turkiet",
  "application_no": "20577/05",
  "hudoc_id": "001-127105",
  "respondent_state": "Turkiet",
  "date": "2013-10-22",
  "danelius_pages": "238",
  "formation": "chamber",
  "ecli": "ECLI:CE:ECHR:2013:1022JUD002057705",
  "importance": "2",
  "doctypebranch": "CHAMBER",
  "separate_opinion": "FALSE",
  "hudoc_docname": "CASE OF SACE ELEKTRİK TİCARET VE SANAYİ A.Ş. v. TURKEY",
  "hudoc_respondent": "TUR",
  "downloaded": true,
  "download_reason": "html",
  "download_render_note": null,
  "attempted_query": "docname:\"CASE OF Ticaret ve Sanayi A.s. v. TURKEY\" AND respondent:\"TUR\"",
  "match_score": 1.5120689655172415,
  "match_name_score": 0.9120689655172414,
  "candidate_count": 47,
  "primary_candidate_itemid": "001-127105",
  "primary_candidate_docname": "CASE OF SACE ELEKTRİK TİCARET VE SANAYİ A.Ş. v. TURKEY"
}